{
	"title": "Form 0",
	"tabs": [{
		"title": "Form 0 title",
		"form": "form_0",
		"id": "form_0",
		"slug": "slug-demo",
		"api": "/api/form-0",
		"edit_btn": true,
		"save_btn": true,
		"delete_btn": true,
		"lines": [
			[
				{
					"id": "firstfield",
					"label": "First field",
					"placeholder": "Text here",
					"element": "input",
					"type": "text",
					"required": true,
					"maxlength": 7,
					"case": "ProperCase",
					"mask": null,
					"pattern": null,
					"readonly": false,
					"helper_text": "Full name",
					"error_text": "Required field",
					"visible_screen": true,
					"autocomplete": false,
					"is_PK": false,
					"is_PK_exist_api": null,
					"search_complete_api": null
				},
				{
					"id": "sizes",
					"label": "Sizes",
					"placeholder": "You sizes",
					"element": "select",
					"required": true,
					"readonly": false,
					"helper_text": "All sizes available",
					"error_text": "Required field",
					"visible_screen": true,
					"options": [
						{
							"value": "example1",
							"text": "Example 1"
						},
						{
							"value": "example2",
							"text": "Example 2"
						},
						{
							"value": "example3",
							"text": "Example 3"
						}
					]
				}
			]
		]
	 }
	]
 }
